sqlalchemy_adapter/__init__.py
sqlalchemy_adapter/adapter.py
sqlalchemy_adapter-1.7.0.dist-info/licenses/LICENSE
sqlalchemy_adapter-1.7.0.dist-info/METADATA
sqlalchemy_adapter-1.7.0.dist-info/WHEEL
sqlalchemy_adapter-1.7.0.dist-info/top_level.txt
sqlalchemy_adapter-1.7.0.dist-info/RECORD
