Metadata-Version: 2.4
Name: sqlalchemy_adapter
Version: 1.7.0
Summary: SQLAlchemy Adapter for PyCasbin
Home-page: https://github.com/officialpycasbin/sqlalchemy-adapter
Author: Casbin
Author-email: admin@casbin.org
License: Apache 2.0
Keywords: pycasbin,casbin,SQLAlchemy,casbin-adapter,rbac,access control,abac,acl,permission
Classifier: Programming Language :: Python :: 3.9
Classifier: Programming Language :: Python :: 3.10
Classifier: Programming Language :: Python :: 3.11
Classifier: Programming Language :: Python :: 3.12
Classifier: License :: OSI Approved :: Apache Software License
Classifier: Operating System :: OS Independent
Requires-Python: >=3.3
License-File: LICENSE
Requires-Dist: pycasbin>=2.0.0
Requires-Dist: SQLAlchemy>=1.2.18
Dynamic: author
Dynamic: author-email
Dynamic: classifier
Dynamic: description
Dynamic: description-content-type
Dynamic: home-page
Dynamic: keywords
Dynamic: license
Dynamic: license-file
Dynamic: requires-dist
Dynamic: requires-python
Dynamic: summary
